jinja2_async/__init__.py
jinja2_async/bccache.py
jinja2_async/compiler.py
jinja2_async/environment.py
jinja2_async/loaders.py
jinja2_async/sandbox.py
jinja2_async-2026.1.30.dist-info/METADATA
jinja2_async-2026.1.30.dist-info/WHEEL
jinja2_async-2026.1.30.dist-info/licenses/LICENSE
jinja2_async-2026.1.30.dist-info/RECORD
