Metadata-Version: 2.4
Name: jinja2-async
Version: 2026.1.30
Summary: Jinja2, but with async template loaders
Project-URL: Homepage, https://github.com/zidsa/jinja2-async
Project-URL: Repository, https://github.com/zidsa/jinja2-async
Project-URL: Issues, https://github.com/zidsa/jinja2-async/issues
Author-email: fatimah <fatimah.alhumaidhi@zid.sa>
License: MIT License
License-File: LICENSE
Keywords: asyncio,jinja,jinja2,templates,templating engine
Classifier: Development Status :: 3 - Alpha
Classifier: Intended Audience :: Developers
Classifier: License :: OSI Approved :: MIT License
Classifier: Operating System :: OS Independent
Classifier: Programming Language :: Python
Classifier: Programming Language :: Python :: 3
Classifier: Programming Language :: Python :: 3 :: Only
Classifier: Programming Language :: Python :: 3.10
Classifier: Programming Language :: Python :: 3.11
Classifier: Programming Language :: Python :: 3.12
Classifier: Programming Language :: Python :: 3.13
Classifier: Programming Language :: Python :: 3.14
Classifier: Typing :: Typed
Requires-Python: >=3.10
Requires-Dist: jinja2>=3.1.6
Provides-Extra: lint
Requires-Dist: mypy>=1.13.0; extra == 'lint'
Requires-Dist: pre-commit>=4.0.0; extra == 'lint'
Requires-Dist: ruff>=0.8.0; extra == 'lint'
Provides-Extra: test
Requires-Dist: coverage[toml]>=7.6.0; extra == 'test'
Requires-Dist: pytest-asyncio>=0.24.0; extra == 'test'
Requires-Dist: pytest>=8.3.0; extra == 'test'
